dirindexer.py
setup.py
DirIndexer.egg-info/PKG-INFO
DirIndexer.egg-info/SOURCES.txt
DirIndexer.egg-info/dependency_links.txt
DirIndexer.egg-info/entry_points.txt
DirIndexer.egg-info/requires.txt
DirIndexer.egg-info/top_level.txt