Metadata-Version: 1.0
Name: DirIndexer
Version: 1.0
Summary: Pure Python command line utility for efficiently indexing then searching a directory
Home-page: https://bitbucket.org/sdbrain/dirindexer/overview
Author: Garrett Greenwood, David Sounthiraraj
Author-email: garrettagreenwood@gmail.com
License: UNKNOWN
Platform: UNKNOWN
